<?xml version="1.0" encoding="UTF-8"?>
<con:soapui-project id="af5683fa-e241-40f7-9fa3-8f0a8707ebd6" activeEnvironment="Default" name="ComexWS" soapui-version="5.7.0" abortOnError="false" runType="SEQUENTIAL" xmlns:con="http://eviware.com/soapui/config"><con:settings/><con:interface xsi:type="con:WsdlInterface" id="5902d2e1-d538-4656-b3c0-53bf8f48b135" wsaVersion="NONE" name="ComexWSPortBinding" type="wsdl" bindingName="{http://ws.comex.com.br/}ComexWSPortBinding" soapVersion="1_1" anonymous="optional" definition="http://localhost:8080/ComexWS?wsdl" xmlns:xsi="http://www.w3.org/2001/XMLSchema-instance"><con:settings/><con:definitionCache type="TEXT" rootPart="http://localhost:8080/ComexWS?wsdl"><con:part><con:url>http://localhost:8080/ComexWS?wsdl</con:url><con:content><![CDATA[<!--Published by JAX-WS RI (http://jax-ws.java.net). RI's version is JAX-WS RI 2.2.9-b130926.1035 svn-revision#5f6196f2b90e9460065a4c2f4e30e065b245e51e.-->
<!--Generated by JAX-WS RI (http://jax-ws.java.net). RI's version is JAX-WS RI 2.2.9-b130926.1035 svn-revision#5f6196f2b90e9460065a4c2f4e30e065b245e51e.-->
<definitions targetNamespace="http://ws.comex.com.br/" name="ComexWSService" xmlns:wsu="http://docs.oasis-open.org/wss/2004/01/oasis-200401-wss-wssecurity-utility-1.0.xsd" xmlns:wsp="http://www.w3.org/ns/ws-policy" xmlns:wsp1_2="http://schemas.xmlsoap.org/ws/2004/09/policy" xmlns:wsam="http://www.w3.org/2007/05/addressing/metadata" xmlns:soap="http://schemas.xmlsoap.org/wsdl/soap/" xmlns:tns="http://ws.comex.com.br/" xmlns:xsd="http://www.w3.org/2001/XMLSchema" xmlns="http://schemas.xmlsoap.org/wsdl/">
  <types>
    <xsd:schema>
      <xsd:import namespace="http://ws.comex.com.br/" schemaLocation="http://localhost:8080/ComexWS?xsd=1"/>
    </xsd:schema>
  </types>
  <message name="listarCategorias">
    <part name="parameters" element="tns:listarCategorias"/>
  </message>
  <message name="listarCategoriasResponse">
    <part name="parameters" element="tns:listarCategoriasResponse"/>
  </message>
  <message name="SQLException">
    <part name="fault" element="tns:SQLException"/>
  </message>
  <message name="listarProdutos">
    <part name="parameters" element="tns:listarProdutos"/>
  </message>
  <message name="listarProdutosResponse">
    <part name="parameters" element="tns:listarProdutosResponse"/>
  </message>
  <message name="AdicionaCategorias">
    <part name="parameters" element="tns:AdicionaCategorias"/>
  </message>
  <message name="AdicionaCategoriasResponse">
    <part name="parameters" element="tns:AdicionaCategoriasResponse"/>
  </message>
  <message name="listarClientes">
    <part name="parameters" element="tns:listarClientes"/>
  </message>
  <message name="listarClientesResponse">
    <part name="parameters" element="tns:listarClientesResponse"/>
  </message>
  <message name="AdicionaClientes">
    <part name="parameters" element="tns:AdicionaClientes"/>
  </message>
  <message name="AdicionaClientesResponse">
    <part name="parameters" element="tns:AdicionaClientesResponse"/>
  </message>
  <portType name="ComexWS">
    <operation name="listarCategorias">
      <input wsam:Action="http://ws.comex.com.br/ComexWS/listarCategoriasRequest" message="tns:listarCategorias"/>
      <output wsam:Action="http://ws.comex.com.br/ComexWS/listarCategoriasResponse" message="tns:listarCategoriasResponse"/>
      <fault message="tns:SQLException" name="SQLException" wsam:Action="http://ws.comex.com.br/ComexWS/listarCategorias/Fault/SQLException"/>
    </operation>
    <operation name="listarProdutos">
      <input wsam:Action="http://ws.comex.com.br/ComexWS/listarProdutosRequest" message="tns:listarProdutos"/>
      <output wsam:Action="http://ws.comex.com.br/ComexWS/listarProdutosResponse" message="tns:listarProdutosResponse"/>
      <fault message="tns:SQLException" name="SQLException" wsam:Action="http://ws.comex.com.br/ComexWS/listarProdutos/Fault/SQLException"/>
    </operation>
    <operation name="AdicionaCategorias">
      <input wsam:Action="http://ws.comex.com.br/ComexWS/AdicionaCategoriasRequest" message="tns:AdicionaCategorias"/>
      <output wsam:Action="http://ws.comex.com.br/ComexWS/AdicionaCategoriasResponse" message="tns:AdicionaCategoriasResponse"/>
      <fault message="tns:SQLException" name="SQLException" wsam:Action="http://ws.comex.com.br/ComexWS/AdicionaCategorias/Fault/SQLException"/>
    </operation>
    <operation name="listarClientes">
      <input wsam:Action="http://ws.comex.com.br/ComexWS/listarClientesRequest" message="tns:listarClientes"/>
      <output wsam:Action="http://ws.comex.com.br/ComexWS/listarClientesResponse" message="tns:listarClientesResponse"/>
      <fault message="tns:SQLException" name="SQLException" wsam:Action="http://ws.comex.com.br/ComexWS/listarClientes/Fault/SQLException"/>
    </operation>
    <operation name="AdicionaClientes">
      <input wsam:Action="http://ws.comex.com.br/ComexWS/AdicionaClientesRequest" message="tns:AdicionaClientes"/>
      <output wsam:Action="http://ws.comex.com.br/ComexWS/AdicionaClientesResponse" message="tns:AdicionaClientesResponse"/>
      <fault message="tns:SQLException" name="SQLException" wsam:Action="http://ws.comex.com.br/ComexWS/AdicionaClientes/Fault/SQLException"/>
    </operation>
  </portType>
  <binding name="ComexWSPortBinding" type="tns:ComexWS">
    <soap:binding transport="http://schemas.xmlsoap.org/soap/http" style="document"/>
    <operation name="listarCategorias">
      <soap:operation soapAction=""/>
      <input>
        <soap:body use="literal"/>
      </input>
      <output>
        <soap:body use="literal"/>
      </output>
      <fault name="SQLException">
        <soap:fault name="SQLException" use="literal"/>
      </fault>
    </operation>
    <operation name="listarProdutos">
      <soap:operation soapAction=""/>
      <input>
        <soap:body use="literal"/>
      </input>
      <output>
        <soap:body use="literal"/>
      </output>
      <fault name="SQLException">
        <soap:fault name="SQLException" use="literal"/>
      </fault>
    </operation>
    <operation name="AdicionaCategorias">
      <soap:operation soapAction=""/>
      <input>
        <soap:body use="literal"/>
      </input>
      <output>
        <soap:body use="literal"/>
      </output>
      <fault name="SQLException">
        <soap:fault name="SQLException" use="literal"/>
      </fault>
    </operation>
    <operation name="listarClientes">
      <soap:operation soapAction=""/>
      <input>
        <soap:body use="literal"/>
      </input>
      <output>
        <soap:body use="literal"/>
      </output>
      <fault name="SQLException">
        <soap:fault name="SQLException" use="literal"/>
      </fault>
    </operation>
    <operation name="AdicionaClientes">
      <soap:operation soapAction=""/>
      <input>
        <soap:body use="literal"/>
      </input>
      <output>
        <soap:body use="literal"/>
      </output>
      <fault name="SQLException">
        <soap:fault name="SQLException" use="literal"/>
      </fault>
    </operation>
  </binding>
  <service name="ComexWSService">
    <port name="ComexWSPort" binding="tns:ComexWSPortBinding">
      <soap:address location="http://localhost:8080/ComexWS"/>
    </port>
  </service>
</definitions>]]></con:content><con:type>http://schemas.xmlsoap.org/wsdl/</con:type></con:part><con:part><con:url>http://localhost:8080/ComexWS?xsd=1</con:url><con:content><![CDATA[<!--Published by JAX-WS RI (http://jax-ws.java.net). RI's version is JAX-WS RI 2.2.9-b130926.1035 svn-revision#5f6196f2b90e9460065a4c2f4e30e065b245e51e.-->
<xs:schema version="1.0" targetNamespace="http://ws.comex.com.br/" xmlns:tns="http://ws.comex.com.br/" xmlns:xs="http://www.w3.org/2001/XMLSchema">
  <xs:element name="AdicionaCategorias" type="tns:AdicionaCategorias"/>
  <xs:element name="AdicionaCategoriasResponse" type="tns:AdicionaCategoriasResponse"/>
  <xs:element name="AdicionaClientes" type="tns:AdicionaClientes"/>
  <xs:element name="AdicionaClientesResponse" type="tns:AdicionaClientesResponse"/>
  <xs:element name="SQLException" type="tns:SQLException"/>
  <xs:element name="categoria" type="tns:categoria"/>
  <xs:element name="listarCategorias" type="tns:listarCategorias"/>
  <xs:element name="listarCategoriasResponse" type="tns:listarCategoriasResponse"/>
  <xs:element name="listarClientes" type="tns:listarClientes"/>
  <xs:element name="listarClientesResponse" type="tns:listarClientesResponse"/>
  <xs:element name="listarProdutos" type="tns:listarProdutos"/>
  <xs:element name="listarProdutosResponse" type="tns:listarProdutosResponse"/>
  <xs:complexType name="AdicionaCategorias">
    <xs:sequence>
      <xs:element name="arg0" type="tns:categoria" minOccurs="0"/>
    </xs:sequence>
  </xs:complexType>
  <xs:complexType name="categoria">
    <xs:sequence>
      <xs:element name="id" type="xs:int"/>
      <xs:element name="nome" type="xs:string" minOccurs="0"/>
      <xs:element name="status" type="tns:statusCategoria" minOccurs="0"/>
    </xs:sequence>
  </xs:complexType>
  <xs:complexType name="AdicionaCategoriasResponse">
    <xs:sequence>
      <xs:element name="Categoria" type="tns:categoria" minOccurs="0"/>
    </xs:sequence>
  </xs:complexType>
  <xs:complexType name="SQLException">
    <xs:sequence>
      <xs:element name="SQLState" type="xs:string" minOccurs="0"/>
      <xs:element name="errorCode" type="xs:int"/>
      <xs:element name="message" type="xs:string" minOccurs="0"/>
      <xs:element name="nextException" type="tns:sqlException" minOccurs="0"/>
    </xs:sequence>
  </xs:complexType>
  <xs:complexType name="sqlException">
    <xs:complexContent>
      <xs:extension base="tns:exception">
        <xs:sequence>
          <xs:element name="nextException" type="tns:sqlException" minOccurs="0"/>
        </xs:sequence>
      </xs:extension>
    </xs:complexContent>
  </xs:complexType>
  <xs:complexType name="exception">
    <xs:complexContent>
      <xs:extension base="tns:throwable">
        <xs:sequence/>
      </xs:extension>
    </xs:complexContent>
  </xs:complexType>
  <xs:complexType name="throwable">
    <xs:sequence>
      <xs:element name="stackTrace" type="tns:stackTraceElement" nillable="true" minOccurs="0" maxOccurs="unbounded"/>
    </xs:sequence>
  </xs:complexType>
  <xs:complexType name="stackTraceElement" final="extension restriction">
    <xs:sequence/>
  </xs:complexType>
  <xs:complexType name="listarClientes">
    <xs:sequence/>
  </xs:complexType>
  <xs:complexType name="listarClientesResponse">
    <xs:sequence>
      <xs:element name="Cliente" type="tns:cliente" minOccurs="0" maxOccurs="unbounded"/>
    </xs:sequence>
  </xs:complexType>
  <xs:complexType name="cliente">
    <xs:sequence>
      <xs:element name="bairro" type="xs:string" minOccurs="0"/>
      <xs:element name="cidade" type="xs:string" minOccurs="0"/>
      <xs:element name="complemento" type="xs:string" minOccurs="0"/>
      <xs:element name="cpf" type="xs:string" minOccurs="0"/>
      <xs:element name="estado" type="tns:clienteEstado" minOccurs="0"/>
      <xs:element name="id" type="xs:int"/>
      <xs:element name="nome" type="xs:string" minOccurs="0"/>
      <xs:element name="numeroRua" type="xs:string" minOccurs="0"/>
      <xs:element name="rua" type="xs:string" minOccurs="0"/>
      <xs:element name="telefone" type="xs:string" minOccurs="0"/>
    </xs:sequence>
  </xs:complexType>
  <xs:complexType name="listarCategorias">
    <xs:sequence/>
  </xs:complexType>
  <xs:complexType name="listarCategoriasResponse">
    <xs:sequence>
      <xs:element name="Categoria" type="tns:categoria" minOccurs="0" maxOccurs="unbounded"/>
    </xs:sequence>
  </xs:complexType>
  <xs:complexType name="AdicionaClientes">
    <xs:sequence>
      <xs:element name="arg0" type="tns:cliente" minOccurs="0"/>
    </xs:sequence>
  </xs:complexType>
  <xs:complexType name="AdicionaClientesResponse">
    <xs:sequence>
      <xs:element name="Cliente" type="tns:cliente" minOccurs="0"/>
    </xs:sequence>
  </xs:complexType>
  <xs:complexType name="listarProdutos">
    <xs:sequence/>
  </xs:complexType>
  <xs:complexType name="listarProdutosResponse">
    <xs:sequence>
      <xs:element name="Produto" type="tns:produto" minOccurs="0" maxOccurs="unbounded"/>
    </xs:sequence>
  </xs:complexType>
  <xs:complexType name="produto">
    <xs:sequence>
      <xs:element name="categoria" type="xs:int"/>
      <xs:element name="descricao" type="xs:string" minOccurs="0"/>
      <xs:element name="id" type="xs:int"/>
      <xs:element name="nome" type="xs:string" minOccurs="0"/>
      <xs:element name="precoUnitario" type="xs:decimal" minOccurs="0"/>
      <xs:element name="qtdEstoque" type="xs:int"/>
      <xs:element name="tipo" type="tns:tipo" minOccurs="0"/>
    </xs:sequence>
  </xs:complexType>
  <xs:simpleType name="statusCategoria">
    <xs:restriction base="xs:string">
      <xs:enumeration value="ATIVA"/>
      <xs:enumeration value="INATIVA"/>
    </xs:restriction>
  </xs:simpleType>
  <xs:simpleType name="clienteEstado">
    <xs:restriction base="xs:string">
      <xs:enumeration value="AC"/>
      <xs:enumeration value="AL"/>
      <xs:enumeration value="AP"/>
      <xs:enumeration value="AM"/>
      <xs:enumeration value="BA"/>
      <xs:enumeration value="CE"/>
      <xs:enumeration value="DF"/>
      <xs:enumeration value="ES"/>
      <xs:enumeration value="GO"/>
      <xs:enumeration value="MA"/>
      <xs:enumeration value="MT"/>
      <xs:enumeration value="MS"/>
      <xs:enumeration value="MG"/>
      <xs:enumeration value="PA"/>
      <xs:enumeration value="PB"/>
      <xs:enumeration value="PR"/>
      <xs:enumeration value="PE"/>
      <xs:enumeration value="PI"/>
      <xs:enumeration value="RJ"/>
      <xs:enumeration value="RN"/>
      <xs:enumeration value="RS"/>
      <xs:enumeration value="RO"/>
      <xs:enumeration value="RR"/>
      <xs:enumeration value="SC"/>
      <xs:enumeration value="SP"/>
      <xs:enumeration value="SE"/>
      <xs:enumeration value="TO"/>
    </xs:restriction>
  </xs:simpleType>
  <xs:simpleType name="tipo">
    <xs:restriction base="xs:string">
      <xs:enumeration value="ISENTO"/>
      <xs:enumeration value="NAO_ISENTO"/>
    </xs:restriction>
  </xs:simpleType>
</xs:schema>]]></con:content><con:type>http://www.w3.org/2001/XMLSchema</con:type></con:part></con:definitionCache><con:endpoints><con:endpoint>http://localhost:8080/ComexWS</con:endpoint></con:endpoints><con:operation id="061ea79f-c6b4-4755-b677-a11e05124a39" isOneWay="false" action="" name="AdicionaCategorias" bindingOperationName="AdicionaCategorias" type="Request-Response" inputName="" receivesAttachments="false" sendsAttachments="false" anonymous="optional"><con:settings/><con:call id="f3d958c7-6eff-4eb7-bc05-cfefc2e722f9" name="Request 1"><con:settings/><con:encoding>UTF-8</con:encoding><con:endpoint>http://localhost:8080/ComexWS</con:endpoint><con:request><![CDATA[<soapenv:Envelope xmlns:soapenv="http://schemas.xmlsoap.org/soap/envelope/" xmlns:ws="http://ws.comex.com.br/">\r
   <soapenv:Header/>\r
   <soapenv:Body>\r
      <ws:AdicionaCategorias>\r
         <!--Optional:-->\r
         <arg0>\r
            <id>?</id>\r
            <!--Optional:-->\r
            <nome>?</nome>\r
            <!--Optional:-->\r
            <status>?</status>\r
         </arg0>\r
      </ws:AdicionaCategorias>\r
   </soapenv:Body>\r
</soapenv:Envelope>]]></con:request><con:wsaConfig mustUnderstand="NONE" version="200508" action="http://ws.comex.com.br/ComexWS/AdicionaCategoriasRequest"/></con:call></con:operation><con:operation id="b866b9ae-3d4e-4d8e-8117-c09820600e33" isOneWay="false" action="" name="AdicionaClientes" bindingOperationName="AdicionaClientes" type="Request-Response" inputName="" receivesAttachments="false" sendsAttachments="false" anonymous="optional"><con:settings/><con:call id="6cf2c9b7-b33b-4e88-9d42-bcf3d3936b66" name="Request 1"><con:settings/><con:encoding>UTF-8</con:encoding><con:endpoint>http://localhost:8080/ComexWS</con:endpoint><con:request><![CDATA[<soapenv:Envelope xmlns:soapenv="http://schemas.xmlsoap.org/soap/envelope/" xmlns:ws="http://ws.comex.com.br/">\r
   <soapenv:Header/>\r
   <soapenv:Body>\r
      <ws:AdicionaClientes>\r
         <!--Optional:-->\r
         <arg0>\r
            <!--Optional:-->\r
            <bairro>?</bairro>\r
            <!--Optional:-->\r
            <cidade>?</cidade>\r
            <!--Optional:-->\r
            <complemento>?</complemento>\r
            <!--Optional:-->\r
            <cpf>?</cpf>\r
            <!--Optional:-->\r
            <estado>?</estado>\r
            <id>?</id>\r
            <!--Optional:-->\r
            <nome>?</nome>\r
            <!--Optional:-->\r
            <numeroRua>?</numeroRua>\r
            <!--Optional:-->\r
            <rua>?</rua>\r
            <!--Optional:-->\r
            <telefone>?</telefone>\r
         </arg0>\r
      </ws:AdicionaClientes>\r
   </soapenv:Body>\r
</soapenv:Envelope>]]></con:request><con:wsaConfig mustUnderstand="NONE" version="200508" action="http://ws.comex.com.br/ComexWS/AdicionaClientesRequest"/></con:call></con:operation><con:operation id="cf80311b-dce3-4e2f-bfbb-3a1272b031d0" isOneWay="false" action="" name="listarCategorias" bindingOperationName="listarCategorias" type="Request-Response" inputName="" receivesAttachments="false" sendsAttachments="false" anonymous="optional"><con:settings/><con:call id="a55ab542-c31a-4bed-81fe-e9271ed44124" name="Request 1"><con:settings><con:setting id="com.eviware.soapui.impl.wsdl.WsdlRequest@request-headers">&lt;xml-fragment/></con:setting></con:settings><con:encoding>UTF-8</con:encoding><con:endpoint>http://localhost:8080/ComexWS</con:endpoint><con:request><![CDATA[<soapenv:Envelope xmlns:soapenv="http://schemas.xmlsoap.org/soap/envelope/" xmlns:ws="http://ws.comex.com.br/">\r
   <soapenv:Header/>\r
   <soapenv:Body>\r
      <ws:listarCategorias/>\r
   </soapenv:Body>\r
</soapenv:Envelope>]]></con:request><con:credentials><con:authType>No Authorization</con:authType></con:credentials><con:jmsConfig JMSDeliveryMode="PERSISTENT"/><con:jmsPropertyConfig/><con:wsaConfig mustUnderstand="NONE" version="200508" action="http://ws.comex.com.br/ComexWS/listarCategoriasRequest"/><con:wsrmConfig version="1.2"/></con:call></con:operation><con:operation id="b67024c6-c6f4-4967-b200-00b308a8c6ab" isOneWay="false" action="" name="listarClientes" bindingOperationName="listarClientes" type="Request-Response" inputName="" receivesAttachments="false" sendsAttachments="false" anonymous="optional"><con:settings/><con:call id="7a4ef7da-0ee5-428e-b5d5-daa515a917c9" name="Request 1"><con:settings><con:setting id="com.eviware.soapui.impl.wsdl.WsdlRequest@request-headers">&lt;xml-fragment/></con:setting></con:settings><con:encoding>UTF-8</con:encoding><con:endpoint>http://localhost:8080/ComexWS</con:endpoint><con:request><![CDATA[<soapenv:Envelope xmlns:soapenv="http://schemas.xmlsoap.org/soap/envelope/" xmlns:ws="http://ws.comex.com.br/">\r
   <soapenv:Header/>\r
   <soapenv:Body>\r
      <ws:listarClientes/>\r
   </soapenv:Body>\r
</soapenv:Envelope>]]></con:request><con:credentials><con:authType>No Authorization</con:authType></con:credentials><con:jmsConfig JMSDeliveryMode="PERSISTENT"/><con:jmsPropertyConfig/><con:wsaConfig mustUnderstand="NONE" version="200508" action="http://ws.comex.com.br/ComexWS/listarClientesRequest"/><con:wsrmConfig version="1.2"/></con:call></con:operation><con:operation id="41cdd276-5443-4bcf-aa85-adc51f3c6b78" isOneWay="false" action="" name="listarProdutos" bindingOperationName="listarProdutos" type="Request-Response" inputName="" receivesAttachments="false" sendsAttachments="false" anonymous="optional"><con:settings/><con:call id="23bf0240-c03b-4d94-96a1-3e1f96da2597" name="Request 1"><con:settings><con:setting id="com.eviware.soapui.impl.wsdl.WsdlRequest@request-headers">&lt;xml-fragment/></con:setting></con:settings><con:encoding>UTF-8</con:encoding><con:endpoint>http://localhost:8080/ComexWS</con:endpoint><con:request><![CDATA[<soapenv:Envelope xmlns:soapenv="http://schemas.xmlsoap.org/soap/envelope/" xmlns:ws="http://ws.comex.com.br/">\r
   <soapenv:Header/>\r
   <soapenv:Body>\r
      <ws:listarProdutos/>\r
   </soapenv:Body>\r
</soapenv:Envelope>]]></con:request><con:credentials><con:authType>No Authorization</con:authType></con:credentials><con:jmsConfig JMSDeliveryMode="PERSISTENT"/><con:jmsPropertyConfig/><con:wsaConfig mustUnderstand="NONE" version="200508" action="http://ws.comex.com.br/ComexWS/listarProdutosRequest"/><con:wsrmConfig version="1.2"/></con:call></con:operation></con:interface><con:properties/><con:wssContainer/><con:oAuth2ProfileContainer/><con:oAuth1ProfileContainer/><con:sensitiveInformation/></con:soapui-project>